{
  "yt_short_formats_used": [
    "did_you_know"
  ],
  "yt_short_music_used": [
    "11_caravan",
    "17_street_beats",
    "21_zen_garden",
    "06_tribal_pulse",
    "26_ritual_sun",
    "15_bossa_sunset",
    "27_sahel_nights",
    "12_velvet_noir"
  ],
  "posted_today": {
    "PdMu0": "2026-04-22",
    "m8EAd": "2026-04-22",
    "m8EAd_reel": "2026-04-22",
    "PdMu0_reel": "2026-04-22",
    "4QL0i_reel": "2026-04-19",
    "m8EAd_canva": "2026-04-20",
    "PdMu0_canva": "2026-04-20",
    "m8EAd_evening": "2026-04-20",
    "m8EAd_evening_story": "2026-04-20",
    "PdMu0_evening": "2026-04-20",
    "m8EAd_yt_short": "2026-04-22",
    "m8EAd_yt_short_count": 1,
    "jUmP2_yt_short": "2026-04-20",
    "jUmP2_yt_short_count": 1,
    "jUmP2": "2026-04-20",
    "m8EAd_moat": "2026-04-22",
    "PdMu0_moat": "2026-04-22",
    "m8EAd_infographic": "2026-04-20",
    "PdMu0_infographic": "2026-04-20",
    "jUmP2_reel": "2026-04-20",
    "m8EAd_tourist_map": "2026-04-21",
    "PdMu0_tourist_map": "2026-04-21",
    "m8EAd_pomelli": "2026-04-21",
    "PdMu0_pomelli": "2026-04-21",
    "36BUk_reel": "2026-04-21",
    "36BUk_yt_short": "2026-04-21",
    "36BUk_yt_short_count": 1
  },
  "last_sync": "2026-04-22T07:12:44.489620+00:00",
  "posted_destinations": [
    {
      "destination_id": "pahalgam",
      "date": "2026-04-19"
    },
    {
      "destination_id": "dhanaulti",
      "date": "2026-04-19"
    },
    {
      "destination_id": "ziro-valley",
      "date": "2026-04-19"
    },
    {
      "destination_id": "ziro-valley",
      "date": "2026-04-19"
    },
    {
      "destination_id": "yercaud",
      "date": "2026-04-19"
    },
    {
      "destination_id": "thrissur",
      "date": "2026-04-19"
    },
    {
      "destination_id": "mudumalai",
      "date": "2026-04-19"
    },
    {
      "destination_id": "kotagiri",
      "date": "2026-04-19"
    },
    {
      "destination_id": "kodaikanal",
      "date": "2026-04-19"
    },
    {
      "destination_id": "ziro-valley",
      "date": "2026-04-19"
    },
    {
      "destination_id": "yercaud",
      "date": "2026-04-19"
    },
    {
      "destination_id": "thrissur",
      "date": "2026-04-19"
    },
    {
      "destination_id": "mudumalai",
      "date": "2026-04-19"
    },
    {
      "destination_id": "kotagiri",
      "date": "2026-04-19"
    },
    {
      "destination_id": "bhimtal",
      "date": "2026-04-20"
    },
    {
      "destination_id": "yt_short_before_after_yt_short_before_after_2026-04-20",
      "date": "2026-04-20"
    },
    {
      "destination_id": "yt_short_mini_guide_yt_short_mini_guide_2026-04-20",
      "date": "2026-04-20"
    },
    {
      "destination_id": "reel_destination_reveal_reel_destination_reveal_ziro-valley",
      "date": "2026-04-20"
    },
    {
      "destination_id": "almora",
      "date": "2026-04-20"
    },
    {
      "destination_id": "almora",
      "date": "2026-04-20"
    },
    {
      "destination_id": "yercaud",
      "date": "2026-04-20"
    },
    {
      "destination_id": "yercaud",
      "date": "2026-04-20"
    },
    {
      "destination_id": "kausani",
      "date": "2026-04-21"
    },
    {
      "destination_id": "palampur",
      "date": "2026-04-21"
    },
    {
      "destination_id": "coonoor",
      "date": "2026-04-22"
    },
    {
      "destination_id": "yt_short_did_you_know_yt_short_did_you_know_2026-04-22",
      "date": "2026-04-22"
    },
    {
      "destination_id": "dirang",
      "date": "2026-04-22"
    },
    {
      "destination_id": "morni-hills",
      "date": "2026-04-22"
    },
    {
      "destination_id": "bandipur",
      "date": "2026-04-22"
    },
    {
      "destination_id": "reel_seasonal_shift_reel_seasonal_shift_yuksom",
      "date": "2026-04-22"
    },
    {
      "destination_id": "manikaran",
      "date": "2026-04-22"
    },
    {
      "destination_id": "manikaran",
      "date": "2026-04-22"
    }
  ],
  "posted_formats": {
    "m8EAd": [
      "monthly_forecast",
      "methodology_roads",
      "score_card",
      "methodology_family"
    ],
    "PdMu0": [
      "monthly_forecast",
      "methodology_roads",
      "score_card",
      "methodology_family"
    ]
  },
  "post_log": [
    {
      "timestamp": "2026-04-19T10:12:14.002758+00:00",
      "date": "2026-04-19",
      "platform": "instagram",
      "account_id": "m8EAd",
      "post_id": "LZCzV",
      "destination": "ziro-valley",
      "format": "monthly_forecast",
      "has_media": true
    },
    {
      "timestamp": "2026-04-19T10:12:36.554864+00:00",
      "date": "2026-04-19",
      "platform": "instagram_story",
      "account_id": "m8EAd",
      "post_id": "3o5Tk",
      "destination": "thrissur",
      "format": "kids_intel",
      "has_media": true,
      "mode": "evening"
    },
    {
      "timestamp": "2026-04-19T10:13:32.590766+00:00",
      "date": "2026-04-19",
      "platform": "facebook",
      "account_id": "PdMu0",
      "post_id": "kcDGh",
      "destination": "kodaikanal",
      "format": "monthly_forecast",
      "has_media": true
    },
    {
      "timestamp": "2026-04-20T06:44:07.172572+00:00",
      "date": "2026-04-20",
      "platform": "instagram",
      "account_id": "m8EAd",
      "post_id": "udx4E",
      "destination": "almora",
      "format": "methodology_roads",
      "has_media": true
    },
    {
      "timestamp": "2026-04-20T06:44:32.679719+00:00",
      "date": "2026-04-20",
      "platform": "facebook",
      "account_id": "PdMu0",
      "post_id": "4JU5i",
      "destination": "almora",
      "format": "methodology_roads",
      "has_media": true
    },
    {
      "timestamp": "2026-04-20T10:10:33.928040+00:00",
      "date": "2026-04-20",
      "platform": "instagram",
      "account_id": "m8EAd",
      "post_id": "8QkKI",
      "destination": "yercaud",
      "format": "score_card",
      "has_media": true
    },
    {
      "timestamp": "2026-04-20T10:11:07.561943+00:00",
      "date": "2026-04-20",
      "platform": "instagram_story",
      "account_id": "m8EAd",
      "post_id": "e2wjr",
      "destination": "yercaud",
      "format": "festival_alert",
      "has_media": true,
      "mode": "evening"
    },
    {
      "timestamp": "2026-04-20T10:11:42.071982+00:00",
      "date": "2026-04-20",
      "platform": "facebook",
      "account_id": "PdMu0",
      "post_id": "i363B",
      "destination": "yercaud",
      "format": "score_card",
      "has_media": true
    },
    {
      "timestamp": "2026-04-22T06:59:13.547211+00:00",
      "date": "2026-04-22",
      "platform": "instagram",
      "account_id": "m8EAd",
      "post_id": "x9uC8",
      "destination": "manikaran",
      "format": "methodology_family",
      "has_media": true
    },
    {
      "timestamp": "2026-04-22T06:59:30.340503+00:00",
      "date": "2026-04-22",
      "platform": "facebook",
      "account_id": "PdMu0",
      "post_id": "PIaV0",
      "destination": "manikaran",
      "format": "methodology_family",
      "has_media": true
    }
  ],
  "theme_usage": {
    "destinations": {
      "ziro-valley": [
        "2026-04-19"
      ],
      "yercaud": [
        "2026-04-19",
        "2026-04-20"
      ],
      "thrissur": [
        "2026-04-19"
      ],
      "mudumalai": [
        "2026-04-19"
      ],
      "kotagiri": [
        "2026-04-19"
      ],
      "kodaikanal": [
        "2026-04-19"
      ],
      "almora": [
        "2026-04-20"
      ],
      "manikaran": [
        "2026-04-22"
      ]
    },
    "reel_formats": {
      "seasonal_shift": [
        "2026-04-19",
        "2026-04-21",
        "2026-04-22"
      ],
      "destination_reveal": [
        "2026-04-21"
      ]
    },
    "reel_seasonal_dests": {
      "bhimtal": [
        "2026-04-19"
      ],
      "bomdila": [
        "2026-04-21"
      ],
      "yuksom": [
        "2026-04-22"
      ]
    },
    "reel_reveal_dests": {
      "yuksom": [
        "2026-04-21"
      ]
    },
    "canva_categories": {
      "mood_shots": [
        "2026-04-19"
      ]
    },
    "canva_images": {
      "mood_shots/munnar_KL_01.jpg": [
        "2026-04-19"
      ]
    },
    "reels": {
      "ziro-valley": [
        "2026-04-19"
      ],
      "kodaikanal": [
        "2026-04-19"
      ],
      "yercaud": [
        "2026-04-20"
      ]
    },
    "festivals": {
      "e0a60b00-abba-4445-a670-ef40e3b8c068": [
        "2026-04-20"
      ]
    },
    "moat_angles": {
      "methodology_roads": [
        "2026-04-20"
      ],
      "methodology_family": [
        "2026-04-22"
      ]
    },
    "audience_tags": {
      "backpackers": [
        "2026-04-20"
      ]
    },
    "articles": {},
    "tourist_map_states": {
      "HP": [
        "2026-04-21"
      ],
      "RJ": [
        "2026-04-21"
      ]
    },
    "tourist_map_combos": {
      "HP_cartographic_dark": [
        "2026-04-21"
      ],
      "RJ_cartographic_dark": [
        "2026-04-21"
      ]
    },
    "pomelli_campaigns": {
      "dangerous_roads": [
        "2026-04-21"
      ]
    },
    "pomelli_images": {
      "pomelli_dangerous_vs_overhyped.png": [
        "2026-04-21"
      ]
    },
    "morning_formats": {},
    "collections": {}
  },
  "infographic": {
    "last_topic_idx": 0,
    "last_theme_idx": 0,
    "last_posted": "2026-04-20"
  },
  "tourist_map_states": {
    "HP": [
      "2026-04-21"
    ]
  }
}